{
    "$schema": "http://json-schema.org/draft-04/schema#",
    "type": "array",
    "items": [
      {
        "type": "object",
        "properties": {
          "document_type": {
            "type": "string"
          },
          "document_name": {
            "type": "string"
          }
        },
        "required": [
          "document_type",
          "document_name"
        ]
      },
      {
        "type": "object",
        "properties": {
          "document_type": {
            "type": "string"
          },
          "document_name": {
            "type": "string"
          }
        },
        "required": [
          "document_type",
          "document_name"
        ]
      },
      {
        "type": "object",
        "properties": {
          "document_type": {
            "type": "string"
          },
          "document_name": {
            "type": "string"
          }
        },
        "required": [
          "document_type",
          "document_name"
        ]
      },
      {
        "type": "object",
        "properties": {
          "document_type": {
            "type": "string"
          },
          "document_name": {
            "type": "string"
          }
        },
        "required": [
          "document_type",
          "document_name"
        ]
      },
      {
        "type": "object",
        "properties": {
          "document_type": {
            "type": "string"
          },
          "document_name": {
            "type": "string"
          }
        },
        "required": [
          "document_type",
          "document_name"
        ]
      },
      {
        "type": "object",
        "properties": {
          "document_type": {
            "type": "string"
          },
          "document_name": {
            "type": "string"
          }
        },
        "required": [
          "document_type",
          "document_name"
        ]
      }
    ]
  }